pyradox/__init__.py
pyradox/config.py
pyradox/error.py
pyradox/format.py
pyradox/image.py
pyradox/token.py
pyradox/worldmap.py
pyradox/datatype/__init__.py
pyradox/datatype/color.py
pyradox/datatype/time.py
pyradox/datatype/tree.py
pyradox/datatype/util.py
pyradox/filetype/__init__.py
pyradox/filetype/csv.py
pyradox/filetype/json.py
pyradox/filetype/table.py
pyradox/filetype/txt.py
pyradox/filetype/yml.py
pyradox_txt_parser-5.0.1.dist-info/METADATA
pyradox_txt_parser-5.0.1.dist-info/WHEEL
pyradox_txt_parser-5.0.1.dist-info/top_level.txt
pyradox_txt_parser-5.0.1.dist-info/RECORD
