Metadata-Version: 2.4
Name: pyradox-txt-parser
Version: 5.0.1
Summary: Parser for Paradox Development Studio game files.
Home-page: https://github.com/ajul/pyradox
Author: Albert Julius Liu
Author-email: ajul1987@gmail.com
Project-URL: Twitter, https://twitter.com/highdiceroller
Classifier: Development Status :: 5 - Production/Stable
Classifier: License :: OSI Approved :: MIT License
Classifier: Programming Language :: Other Scripting Engines
Classifier: Programming Language :: Python :: 3
Classifier: Topic :: Games/Entertainment
Requires-Python: >=3.10
Provides-Extra: worldmap
Requires-Dist: pillow; extra == "worldmap"
